bdarpack/CleanData.py
bdarpack/Constraints.py
bdarpack/GaussianCopula.py
bdarpack/MarginalDist.py
bdarpack/PrivacyMetric.py
bdarpack/TabulaCopula.py
bdarpack/Transformer.py
bdarpack/VIsualPlot.py
bdarpack/__init__.py
bdarpack/utils_.py
bdarpack/utils_exec.py
bdarpack/tests/__init__.py
bdarpack/tests/definitions.py
bdarpack/tests/definitions_date.py
bdarpack/tests/script_nhanes_constraints.py
bdarpack/tests/test_clean.py
bdarpack/tests/test_transformer.py
bdarpack-0.1.10.dist-info/licenses/LICENSE
bdarpack-0.1.10.dist-info/METADATA
bdarpack-0.1.10.dist-info/WHEEL
bdarpack-0.1.10.dist-info/top_level.txt
bdarpack-0.1.10.dist-info/RECORD
