Metadata-Version: 2.4
Name: bdarpack
Version: 0.1.10
Summary: A Python package for tabular synthetic data
Home-page: https://biomeddar.github.io/copula-tabular/
Author: MZ Tan
Author-email: tan_ming_zhen@bii.a-star.edu.sg
License: MIT
Keywords: synthetic data copula
Classifier: Development Status :: 4 - Beta
Classifier: Intended Audience :: Science/Research
Classifier: License :: OSI Approved :: MIT License
Classifier: Operating System :: OS Independent
Classifier: Programming Language :: Python :: 3
Requires-Python: >=3
License-File: LICENSE
Requires-Dist: pandas
Requires-Dist: numpy
Requires-Dist: matplotlib
Requires-Dist: scipy
Requires-Dist: openpyxl
Requires-Dist: scikit-learn
Requires-Dist: xlrd
Requires-Dist: Unidecode
Dynamic: author
Dynamic: author-email
Dynamic: classifier
Dynamic: description
Dynamic: description-content-type
Dynamic: home-page
Dynamic: keywords
Dynamic: license
Dynamic: license-file
Dynamic: requires-dist
Dynamic: requires-python
Dynamic: summary
